mycodes/__init__.py
mycodes/__version__.py
mycodes/cbow.py
mycodes/cnn_cifar.py
mycodes/cnn_mnist.py
mycodes/credit_autoencoder.py
mycodes/ecg_autoencoder.py
mycodes/fnn_cifar.py
mycodes/fnn_mnist.py
mycodes/object_detection.py
mycodes/__pycache__/__init__.cpython-311.pyc
mycodes/__pycache__/__version__.cpython-311.pyc
mycodes_annie-0.1.2.dist-info/licenses/LICENSE
mycodes_annie-0.1.2.dist-info/METADATA
mycodes_annie-0.1.2.dist-info/WHEEL
mycodes_annie-0.1.2.dist-info/top_level.txt
mycodes_annie-0.1.2.dist-info/RECORD
