Metadata-Version: 2.4
Name: mycodes_annie
Version: 0.1.2
Summary: ML scripts bundle (CNN/FNN/Autoencoders/CBOW)
Author: Your Name
License: MIT
Classifier: Programming Language :: Python :: 3
Classifier: License :: OSI Approved :: MIT License
Classifier: Operating System :: OS Independent
Requires-Python: >=3.8
License-File: LICENSE
Dynamic: license-file
